[
    {
        "pregunta": "¿Qué etiqueta HTML5 se usa para reproducir video?",
        "opciones": [
            "<movie>",
            "<video>",
            "<media>",
            "<film>"
        ],
        "respuesta": 1,
        "explicacion": "Soporta mp4, webm, ogg."
    },
    {
        "pregunta": "¿Qué etiqueta HTML5 se usa para reproducir audio?",
        "opciones": [
            "<audio>",
            "<sound>",
            "<music>",
            "<play>"
        ],
        "respuesta": 0,
        "explicacion": "Soporta mp3, wav, ogg."
    },
    {
        "pregunta": "¿Qué atributo añade controles de reproducción (play, pausa, volumen)?",
        "opciones": [
            "buttons",
            "player",
            "controls",
            "ui"
        ],
        "respuesta": 2,
        "explicacion": "Sin este atributo, el usuario no puede controlar el medio por defecto."
    },
    {
        "pregunta": "¿Qué atributo hace que el video se reproduzca automáticamente?",
        "opciones": [
            "play",
            "auto",
            "start",
            "autoplay"
        ],
        "respuesta": 3,
        "explicacion": "A menudo requiere 'muted' para funcionar en navegadores modernos."
    },
    {
        "pregunta": "¿Qué atributo repite el video/audio indefinidamente?",
        "opciones": [
            "again",
            "cycle",
            "loop",
            "repeat"
        ],
        "respuesta": 2,
        "explicacion": "Útil para fondos o música ambiental."
    },
    {
        "pregunta": "¿Qué formato de video es el más compatible en la web?",
        "opciones": [
            "MOV",
            "WMV",
            "AVI",
            "MP4 (H.264)"
        ],
        "respuesta": 3,
        "explicacion": "Funciona en casi todos los navegadores."
    },
    {
        "pregunta": "¿Qué es el atributo 'poster' en la etiqueta video?",
        "opciones": [
            "Los subtítulos",
            "Una imagen que se muestra mientras el video descarga o hasta que el usuario le da a play",
            "Un cartel",
            "El título"
        ],
        "respuesta": 1,
        "explicacion": "Mejora la estética antes de la reproducción."
    },
    {
        "pregunta": "¿Cómo se añaden subtítulos a un video HTML5?",
        "opciones": [
            "Con <text>",
            "Con la etiqueta <track>",
            "Con <subtitle>",
            "Pegados en el video"
        ],
        "respuesta": 1,
        "explicacion": "Usan formato VTT (Web Video Text Tracks)."
    },
    {
        "pregunta": "¿Qué es un códec?",
        "opciones": [
            "Un archivo",
            "Una pantalla",
            "Software/Hardware que comprime y descomprime datos de audio/video",
            "Un reproductor"
        ],
        "respuesta": 2,
        "explicacion": "Coder-Decoder."
    },
    {
        "pregunta": "¿Qué es el Streaming?",
        "opciones": [
            "Televisión",
            "Reproducción de contenido multimedia mientras se descarga, sin esperar a que baje completo",
            "Un río",
            "Descarga directa"
        ],
        "respuesta": 1,
        "explicacion": "Netflix, YouTube, Spotify."
    },
    {
        "pregunta": "¿Qué es el Bitrate?",
        "opciones": [
            "El tamaño de pantalla",
            "El precio",
            "La duración",
            "La cantidad de datos procesados por unidad de tiempo (calidad del video/audio)"
        ],
        "respuesta": 3,
        "explicacion": "A mayor bitrate, mayor calidad y peso."
    },
    {
        "pregunta": "¿Qué es SVG?",
        "opciones": [
            "Un audio",
            "Un texto",
            "Un video",
            "Un formato de gráficos vectoriales basado en XML"
        ],
        "respuesta": 3,
        "explicacion": "Se puede animar y estilizar con CSS."
    },
    {
        "pregunta": "¿Qué es Canvas?",
        "opciones": [
            "Un mapa",
            "Un lienzo de pintura",
            "Una imagen estática",
            "Un elemento HTML5 para dibujar gráficos 2D/3D mediante Scripting (JS)"
        ],
        "respuesta": 3,
        "explicacion": "Usado para juegos y visualizaciones complejas."
    },
    {
        "pregunta": "¿Qué diferencia principal hay entre SVG y Canvas?",
        "opciones": [
            "Canvas es vectorial",
            "SVG es para fotos",
            "Son iguales",
            "SVG es vectorial (DOM) y escala bien; Canvas es mapa de bits (píxeles) y muy rápido para muchos objetos"
        ],
        "respuesta": 3,
        "explicacion": "SVG retiene el modo retenido, Canvas el modo inmediato."
    },
    {
        "pregunta": "¿Qué es WebGL?",
        "opciones": [
            "Un juego",
            "Un video",
            "API de JS para renderizar gráficos 3D en el navegador (usa Canvas)",
            "Una web"
        ],
        "respuesta": 2,
        "explicacion": "Aceleración por hardware."
    },
    {
        "pregunta": "¿Qué es un Podcast?",
        "opciones": [
            "Una serie de archivos de audio digital episódicos que un usuario puede descargar o escuchar",
            "Un blog",
            "Una radio",
            "Un video"
        ],
        "respuesta": 0,
        "explicacion": "Formato de audio muy popular."
    },
    {
        "pregunta": "¿Qué es la relación de aspecto (Aspect Ratio)?",
        "opciones": [
            "El color",
            "La proporción entre el ancho y el alto de una imagen o pantalla (ej. 16:9)",
            "La resolución",
            "El tamaño"
        ],
        "respuesta": 1,
        "explicacion": "16:9 es panorámico estándar."
    },
    {
        "pregunta": "¿Qué es la resolución?",
        "opciones": [
            "El contraste",
            "El número de píxeles que componen la imagen (ancho x alto)",
            "El brillo",
            "El tamaño en pulgadas"
        ],
        "respuesta": 1,
        "explicacion": "1920x1080 es Full HD."
    },
    {
        "pregunta": "¿Qué es un GIF animado?",
        "opciones": [
            "Un video con sonido",
            "Una imagen que contiene varios fotogramas y se reproduce en bucle",
            "Un texto",
            "Una foto estática"
        ],
        "respuesta": 1,
        "explicacion": "Limitado a 256 colores."
    },
    {
        "pregunta": "¿Qué etiqueta se usaba antiguamente para Flash (obsoleto)?",
        "opciones": [
            "<movie>",
            "<play>",
            "<flash>",
            "<object> o <embed>"
        ],
        "respuesta": 3,
        "explicacion": "Flash murió en 2020."
    }
]